odoo/addons/partner_bank_code/README.rst
odoo/addons/partner_bank_code/__init__.py
odoo/addons/partner_bank_code/__manifest__.py
odoo/addons/partner_bank_code/i18n/partner_bank_code.pot
odoo/addons/partner_bank_code/models/__init__.py
odoo/addons/partner_bank_code/models/res_bank.py
odoo/addons/partner_bank_code/readme/CONTRIBUTORS.rst
odoo/addons/partner_bank_code/readme/DESCRIPTION.rst
odoo/addons/partner_bank_code/readme/USAGE.rst
odoo/addons/partner_bank_code/static/description/icon.png
odoo/addons/partner_bank_code/static/description/index.html
odoo/addons/partner_bank_code/views/res_bank.xml
odoo14_addon_partner_bank_code-14.0.1.1.0.dist-info/METADATA
odoo14_addon_partner_bank_code-14.0.1.1.0.dist-info/WHEEL
odoo14_addon_partner_bank_code-14.0.1.1.0.dist-info/top_level.txt
odoo14_addon_partner_bank_code-14.0.1.1.0.dist-info/RECORD
