Metadata-Version: 2.1
Name: odoo14-addon-partner-bank-code
Version: 14.0.1.1.0
Summary: Add fields information in banks
Home-page: https://github.com/OCA/partner-contact
Author: Ecosoft, Odoo Community Association (OCA)
Author-email: support@odoo-community.org
License: AGPL-3
Platform: UNKNOWN
Classifier: Programming Language :: Python
Classifier: Framework :: Odoo
Classifier: License :: OSI Approved :: GNU Affero General Public License v3
Requires-Python: >=3.6
Requires-Dist: odoo (<14.1dev,>=14.0a)
